{
  "schema_version": 1,
  "character_key": "lili",
  "display_name_zh": "莉莉",
  "section_names": {
    "Heat": "热能",
    "n": "站立技",
    "f": "前方向技",
    "df": "前下方向技",
    "d": "下方向技",
    "db": "后下方向技",
    "b": "后方向技",
    "u": "上方向技",
    "Motion Input": "位移指令技",
    "Crouch": "蹲伏技",
    "WS": "起身技",
    "DEW (Dew Glide)": "朝露滑步",
    "RAB (Feisty Rabbit)": "狂兔",
    "BT": "背身技",
    "Others": "其他招式",
    "Throws": "投技"
  },
  "stance_names": {
    "H": "热能中",
    "R": "愤怒中",
    "FC": "蹲伏中",
    "WS": "起身中",
    "SS": "横移中",
    "BT": "背身时",
    "wr": "跑动中",
    "DEW": "朝露滑步",
    "RAB": "狂兔",
    "(Wall_Splat)": "撞墙时"
  },
  "move_names": {
    "Lili-2+3": "热能爆发",
    "Lili-H.2+3": "千年蔷薇·中强音",
    "Lili-H.BT.2+3": "巨蔷薇·中强音",
    "Lili-3,1": "孔雀圆舞曲",
    "Lili-3+4": "黑天鹅",
    "Lili-DEW.2,1": "夜曲",
    "Lili-BT.1,4": "天蝎之刺",
    "Lili-RAB.2": "野兔之歌",
    "Lili-1,2,H.4": "左右·穿刺荆棘",
    "Lili-3+4,H.3+4": "白天鹅·中弱音",
    "Lili-H.f,F+3+4": "穿刺荆棘",
    "Lili-DEW.1,H.4": "玫瑰·穿刺荆棘",
    "Lili-H.RAB.2": "野兔之歌",
    "Lili-H.RAB.3": "野兔之舞",
    "Lili-H.RAB.4": "野兔·穿刺荆棘",
    "Lili-1": "刺拳",
    "Lili-1,1": "刺拳·肘击",
    "Lili-1,1,3": "三色旗",
    "Lili-1,2": "左右直刺",
    "Lili-1,2,3": "左右·后击",
    "Lili-1,2,4": "左右·穿刺荆棘",
    "Lili-2": "右刺拳",
    "Lili-2,3": "日升日落",
    "Lili-2,4": "就寝时刻",
    "Lili-3": "中段左踢",
    "Lili-3,2": "中段左踢·右拳",
    "Lili-3,2,3": "孔雀摇摆舞",
    "Lili-4": "右高踢",
    "Lili-1+2": "破碎之心",
    "Lili-f+2": "前右拳",
    "Lili-f+2,3": "火星之剑",
    "Lili-f+3": "回旋膝",
    "Lili-f+4": "公羊冲撞",
    "Lili-f+1+2": "猫爪",
    "Lili-f+3+4": "日晷",
    "Lili-f+3+4,3": "日晷·二",
    "Lili-f+3+4,3,4": "花环连踢",
    "Lili-df+1": "中段左拳",
    "Lili-df+2": "奥尔良之剑",
    "Lili-df+3": "屈从之踵",
    "Lili-df+4": "中段膝",
    "Lili-df+4,4": "支配之踵",
    "Lili-df+3+4": "后空翻",
    "Lili-df+3+4,3+4": "后空翻·旋刃",
    "Lili-d+1": "下段刺拳",
    "Lili-d+1,2": "下刺拳·右拳",
    "Lili-d+1,2,4": "沉郁哀愁",
    "Lili-d+2": "中段右拳",
    "Lili-d+2,2": "中段右拳·二",
    "Lili-d+2,2,3": "血色假面·尖钉",
    "Lili-d+2,2,4": "血色假面·长枪",
    "Lili-d+3": "荆棘之鞭",
    "Lili-d+4": "右下段踢",
    "Lili-d+1+2": "船歌",
    "Lili-d+3+4": "马特洪峰攀升",
    "Lili-db+1": "潜身刺拳",
    "Lili-db+2": "潜身右拳",
    "Lili-db+3": "命运扭转",
    "Lili-db+4": "雪绒花",
    "Lili-db+3+4": "小苍兰突刺",
    "Lili-b+1": "爱丽舍·伸臂",
    "Lili-b+1,4": "爱丽舍·伸臂回旋",
    "Lili-b+2": "后撤右拳",
    "Lili-b+2,1": "后撤右拳·肘击",
    "Lili-b+2,1,1+2": "天芥菜胸花",
    "Lili-b+3": "狂兔",
    "Lili-b+1+2": "石斛兰",
    "Lili-b+3+4": "镜像",
    "Lili-b+1+3": "攻击返技",
    "Lili-b+1+4": "穿刺荆棘·极强音",
    "Lili-u+3": "上跳中踢",
    "Lili-u+3,3": "上跳中踢·二",
    "Lili-u+3,3,3+4": "月面翻·六出花",
    "Lili-u+4": "上跳踢",
    "Lili-u+1+2": "鞭笞鸢尾",
    "Lili-u+1+2*": "鞭笞鸢尾·二转",
    "Lili-u+1+2**": "鞭笞鸢尾·强音",
    "Lili-u+3+4": "神圣之步",
    "Lili-uf+1": "破碎王冠",
    "Lili-uf+2": "刺荨麻",
    "Lili-uf+3": "摩羯踢",
    "Lili-uf+4": "跃身中踢",
    "Lili-uf+4,3": "向日葵长枪",
    "Lili-uf+3+4": "天使之膝",
    "Lili-uf+3+4,3": "天使之膝·前踢",
    "Lili-uf+3+4,3+4": "天使之膝·升天",
    "Lili-uf,n,4": "延迟升趾踢",
    "Lili-f,F+2": "伸臂突刺",
    "Lili-f,F+3": "前冲踢",
    "Lili-f,F+3,3+4": "六出花",
    "Lili-f,F+4": "万恶之源",
    "Lili-f,F+3+4": "穿刺荆棘",
    "Lili-f,f,F+3": "军刀斩",
    "Lili-f,f,F+1+2": "风雨兰",
    "Lili-FC.1": "蹲姿刺拳",
    "Lili-FC.2": "蹲姿右拳",
    "Lili-FC.3": "蹲姿下踢",
    "Lili-FC.4": "蹲姿胫踢",
    "Lili-FC.df+1": "斩击藤蔓",
    "Lili-FC.df+3": "地平滑步",
    "Lili-FC.df+4": "半月",
    "Lili-ws1": "起身左拳",
    "Lili-ws1,2": "起身左拳·右拳",
    "Lili-ws1,2,4": "忧郁雏菊",
    "Lili-ws2": "纤柔升拳",
    "Lili-ws3": "起身中踢",
    "Lili-ws3,4": "金银花",
    "Lili-ws4": "手杖击",
    "Lili-qcf": "朝露滑步",
    "Lili-DEW.1": "玫瑰",
    "Lili-DEW.1,2": "玫瑰·刺击",
    "Lili-DEW.1,4": "玫瑰·穿刺荆棘",
    "Lili-DEW.2": "朝露突拳",
    "Lili-DEW.3": "铂金之雅",
    "Lili-DEW.1+2": "天使之心",
    "Lili-DEW.3+4": "景泰蓝",
    "Lili-b+3*": "狂兔·第二式",
    "Lili-RAB.3": "野兔之舞",
    "Lili-RAB.4": "野兔·穿刺荆棘",
    "Lili-H.b+3*": "狂兔·第二式·热",
    "Lili-BT.1": "背身左拳",
    "Lili-BT.1,2": "菲耶尔布瓦之剑",
    "Lili-BT.2": "花剑·折断",
    "Lili-BT.3": "背身中踢",
    "Lili-BT.3,4": "彩虹",
    "Lili-BT.4": "剪刀",
    "Lili-BT.4,3+4": "剪刀·旋刃",
    "Lili-BT.1+2": "暴风雨",
    "Lili-BT.3+4": "扭身后空翻",
    "Lili-BT.d+2": "花瓣扫",
    "Lili-BT.d+3": "背身下踢",
    "Lili-BT.d+3,4": "秋风",
    "Lili-BT.d+4": "优雅下踢",
    "Lili-BT.d+3+4": "兰花环",
    "Lili-BT.b+3": "狂兔",
    "Lili-R.df+1+2": "玫瑰人生·极强音",
    "Lili-1+2+3+4": "蓄气",
    "Lili-SS.3": "惊艳趾踢",
    "Lili-SS.4": "半月",
    "Lili-SS.1+2": "小步舞曲",
    "Lili-(back_to_wall).b,b,UB": "蹬墙后空翻",
    "Lili-1+3": "虔诚之吻",
    "Lili-2+4": "蛇蝎美人",
    "Lili-Left_throw": "太阳",
    "Lili-Right_throw": "摩纳哥旋摔",
    "Lili-Back_throw": "蹂躏之美",
    "Lili-uf+1+2": "大王花",
    "Lili-(Wall_Splat).1+3": "飞燕草"
  }
}
